<?xml encoding="UTF-8" version="1.0"?>
<actions>
<action>
	<icon>utilities-terminal</icon>
	<name>Open Terminal Here</name>
	<unique-id>1389320228338470-1</unique-id>
	<command>exo-open --working-directory %f --launch TerminalEmulator</command>
	<description>Example for a custom action</description>
	<patterns>*</patterns>
	<startup-notify/>
	<directories/>
</action>
<action>
	<icon>video-x-generic-symbolic</icon>
	<name>Mediagrid</name>
	<unique-id>1458331891626627-2</unique-id>
	<command>$HOME/tsnap/mediagrid/mediagrid %F</command>
	<description>Mediagrid</description>
	<patterns>*;*.MOV</patterns>
	<directories/>
	<audio-files/>
	<image-files/>
	<other-files/>
	<text-files/>
	<video-files/>
</action>
</actions>
